llmatex/__init__.py
llmatex/main.py
llmatex/prompts.py
llmatex/render.py
llmatex-0.1.0.dist-info/LICENSE
llmatex-0.1.0.dist-info/METADATA
llmatex-0.1.0.dist-info/WHEEL
llmatex-0.1.0.dist-info/entry_points.txt
llmatex-0.1.0.dist-info/RECORD
